firefox_to_sqlite/__init__.py
firefox_to_sqlite/__main__.py
firefox_to_sqlite/cli.py
firefox_to_sqlite/lib.py
firefox_to_sqlite-0.5.0.dist-info/LICENSE
firefox_to_sqlite-0.5.0.dist-info/METADATA
firefox_to_sqlite-0.5.0.dist-info/WHEEL
firefox_to_sqlite-0.5.0.dist-info/entry_points.txt
firefox_to_sqlite-0.5.0.dist-info/RECORD
