Metadata-Version: 2.1
Name: firefox-to-sqlite
Version: 0.5.0
Summary: Create an SQLite database from your Firefox data
Author: Cade Ekblad-Frank
Author-email: cade@e-f.me
Requires-Python: >=3.11,<4.0
Classifier: Programming Language :: Python :: 3
Classifier: Programming Language :: Python :: 3.11
Classifier: Programming Language :: Python :: 3.12
Requires-Dist: sqlite-utils (>=3.36,<4.0)
Requires-Dist: typer[all] (>=0.9.0,<0.10.0)
Project-URL: Documentation, https://firefox-to-sqlite.cade.pro
Project-URL: Repository, https://github.com/cadeef/firefox-to-sqlite
